ark/__init__.py
ark/cli.py
ark/global_constants.py
ark/client/comm_handler/__init__.py
ark/client/comm_handler/comm_handler.py
ark/client/comm_handler/listener.py
ark/client/comm_handler/multi_channel_listener.py
ark/client/comm_handler/multi_channel_publisher.py
ark/client/comm_handler/multi_comm_handler.py
ark/client/comm_handler/publisher.py
ark/client/comm_handler/service.py
ark/client/comm_handler/subscriber.py
ark/client/comm_infrastructure/__init__.py
ark/client/comm_infrastructure/base_node.py
ark/client/comm_infrastructure/comm_endpoint.py
ark/client/comm_infrastructure/endpoint.py
ark/client/comm_infrastructure/hybrid_node.py
ark/client/comm_infrastructure/instance_node.py
ark/client/comm_infrastructure/registry.py
ark/client/comm_infrastructure/script_node.py
ark/client/frequencies/rate.py
ark/client/frequencies/stepper.py
ark/env/ark_env.py
ark/env/spaces.py
ark/system/__init__.py
ark/system/component/__init__.py
ark/system/component/base_component.py
ark/system/component/robot.py
ark/system/component/sensor.py
ark/system/component/sim_component.py
ark/system/driver/__init__.py
ark/system/driver/component_driver.py
ark/system/driver/robot_driver.py
ark/system/driver/sensor_driver.py
ark/system/pybullet/pybullet_backend.py
ark/system/pybullet/pybullet_camera_driver.py
ark/system/pybullet/pybullet_lidar_driver.py
ark/system/pybullet/pybullet_multibody.py
ark/system/pybullet/pybullet_robot_driver.py
ark/system/simulation/__init__.py
ark/system/simulation/simulator_backend.py
ark/system/simulation/simulator_node.py
ark/tools/__init__.py
ark/tools/launcher.py
ark/tools/log.py
ark/tools/network.py
ark/tools/urdf_infos.py
ark/tools/ark_graph/__init__.py
ark/tools/ark_graph/ark_graph.py
ark/tools/data_logging/__init__.py
ark/tools/data_logging/lcm_to_csv.py
ark/tools/juypter_tools/__init__.py
ark/tools/juypter_tools/juypter_tools.py
ark/tools/ros_bridge/__init__.py
ark/tools/ros_bridge/ark_ros_bridge.py
ark/tools/visualization/image_viewer.py
ark_robotics-0.1.1.dist-info/licenses/LICENCE
ark_robotics-0.1.1.dist-info/METADATA
ark_robotics-0.1.1.dist-info/WHEEL
ark_robotics-0.1.1.dist-info/entry_points.txt
ark_robotics-0.1.1.dist-info/top_level.txt
ark_robotics-0.1.1.dist-info/RECORD
