Metadata-Version: 2.4
Name: ark-robotics
Version: 0.1.1
Summary: Robotics Ark robotics framework
Author: Sarthak Das
License: 
Project-URL: Source, https://github.com/Robotics-Ark/ark_framework
Classifier: Programming Language :: Python :: 3
Classifier: License :: OSI Approved :: MIT License
Classifier: Operating System :: OS Independent
Requires-Python: >=3.10
License-File: LICENCE
Requires-Dist: lcm
Requires-Dist: colorlog
Requires-Dist: opencv-python
Requires-Dist: gymnasium
Requires-Dist: matplotlib
Requires-Dist: pandas
Requires-Dist: numpy==1.24.3
Requires-Dist: PyYAML
Requires-Dist: typer
Requires-Dist: graphviz
Requires-Dist: scipy
Requires-Dist: pybullet; sys_platform == "linux"
Provides-Extra: test
Requires-Dist: pytest; extra == "test"
Dynamic: license-file
